testformyclassmodules1/__init__.py
testformyclassmodules1/testformyclassfile1.py
testformyclass1-0.1.0.dist-info/LICENSE
testformyclass1-0.1.0.dist-info/METADATA
testformyclass1-0.1.0.dist-info/WHEEL
testformyclass1-0.1.0.dist-info/top_level.txt
testformyclass1-0.1.0.dist-info/RECORD
