Metadata-Version: 2.1
Name: testformyclass1
Version: 0.1.0
Summary: An NLP python package for computing Boilerplate score and many other text features.
Home-page: https://github.com/myNKUST/testformyclass.git
Author: timenet2300
Author-email: timenet2300@gmail.com
Keywords: Text Mining,Data Science
Classifier: Development Status :: 4 - Beta
Classifier: Programming Language :: Python :: 3
Classifier: Programming Language :: Python :: 3.6
Classifier: Programming Language :: Python :: 3.7
Classifier: Programming Language :: Python :: 3.8
Classifier: Programming Language :: Python :: 3.9
Classifier: License :: OSI Approved :: BSD License
Classifier: Intended Audience :: Developers
Classifier: Intended Audience :: Other Audience
Classifier: Intended Audience :: Science/Research
Classifier: Intended Audience :: Education
Classifier: Topic :: Text Processing
Classifier: Operating System :: Microsoft :: Windows
Classifier: Operating System :: OS Independent
License-File: LICENSE
Requires-Dist: pandas (~=1.2.4)
